leveldb_shelve/__init__.py
leveldb_shelve/leveldb_map.py
leveldb_shelve/leveldb_shelve.py
leveldb_shelve-0.1.1.dist-info/LICENSE
leveldb_shelve-0.1.1.dist-info/METADATA
leveldb_shelve-0.1.1.dist-info/WHEEL
leveldb_shelve-0.1.1.dist-info/top_level.txt
leveldb_shelve-0.1.1.dist-info/RECORD
