Metadata-Version: 2.1
Name: leveldb-shelve
Version: 0.1.1
Summary: LevelDB Backend for shelve module
Home-page: https://github.com/ydotk/leveldb_shelve
Author: Yury Kulazhenkov
Author-email: kulazhenkov@gmail.com
License: UNKNOWN
Platform: UNKNOWN
Classifier: Programming Language :: Python :: 3
Classifier: License :: OSI Approved :: MIT License
Classifier: Operating System :: OS Independent
Requires-Dist: plyvel
